tibiapy/__init__.py
tibiapy/client.py
tibiapy/enums.py
tibiapy/errors.py
tibiapy/urls.py
tibiapy/utils.py
tibiapy/builders/__init__.py
tibiapy/builders/bazaar.py
tibiapy/builders/character.py
tibiapy/builders/creature.py
tibiapy/builders/event.py
tibiapy/builders/forum.py
tibiapy/builders/guild.py
tibiapy/builders/highscores.py
tibiapy/builders/house.py
tibiapy/builders/kill_statistics.py
tibiapy/builders/leaderboard.py
tibiapy/builders/news.py
tibiapy/builders/spell.py
tibiapy/builders/world.py
tibiapy/models/__init__.py
tibiapy/models/base.py
tibiapy/models/bazaar.py
tibiapy/models/character.py
tibiapy/models/creature.py
tibiapy/models/event.py
tibiapy/models/fansite.py
tibiapy/models/forum.py
tibiapy/models/guild.py
tibiapy/models/highscores.py
tibiapy/models/house.py
tibiapy/models/kill_statistics.py
tibiapy/models/leaderboard.py
tibiapy/models/news.py
tibiapy/models/pagination.py
tibiapy/models/spell.py
tibiapy/models/tibia_response.py
tibiapy/models/world.py
tibiapy/parsers/__init__.py
tibiapy/parsers/bazaar.py
tibiapy/parsers/character.py
tibiapy/parsers/creature.py
tibiapy/parsers/event.py
tibiapy/parsers/fansite.py
tibiapy/parsers/forum.py
tibiapy/parsers/guild.py
tibiapy/parsers/highscores.py
tibiapy/parsers/house.py
tibiapy/parsers/kill_statistics.py
tibiapy/parsers/leaderboard.py
tibiapy/parsers/news.py
tibiapy/parsers/spell.py
tibiapy/parsers/world.py
tibia.py-6.3.0.dist-info/LICENSE
tibia.py-6.3.0.dist-info/METADATA
tibia.py-6.3.0.dist-info/WHEEL
tibia.py-6.3.0.dist-info/top_level.txt
tibia.py-6.3.0.dist-info/RECORD
