Metadata-Version: 2.1
Name: tibia.py
Version: 6.3.0
Summary: API that parses website content into python data.
Author-email: Allan Galarza <allan.galarza@gmail.com>
Maintainer-email: Allan Galarza <allan.galarza@gmail.com>
License: Apache 2.0
Project-URL: Homepage, https://tibiapy.readthedocs.io/
Project-URL: Documentation, https://tibiapy.readthedocs.io/
Project-URL: Repository, https://github.com/Galarzaa90/tibia.py
Project-URL: Changelog, https://tibiapy.readthedocs.io/en/latest/changelog.html
Project-URL: GitHub: Issues, https://github.com/Galarzaa90/tibia.py/issues
Project-URL: Coverage: Codecov, https://app.codecov.io/gh/Galarzaa90/tibia.py
Project-URL: Docker Hub: Repo, https://hub.docker.com/repository/docker/galarzaa90/tibia.py
Project-URL: SonarCloud, https://sonarcloud.io/dashboard?id=Galarzaa90_tibia.py
Classifier: Development Status :: 5 - Production/Stable
Classifier: Framework :: Pydantic :: 2
Classifier: Framework :: Pydantic
Classifier: Intended Audience :: Developers
Classifier: License :: OSI Approved :: Apache Software License
Classifier: Natural Language :: English
Classifier: Operating System :: OS Independent
Classifier: Programming Language :: Python :: 3 :: Only
Classifier: Programming Language :: Python :: 3.8
Classifier: Programming Language :: Python :: 3.9
Classifier: Programming Language :: Python :: 3.10
Classifier: Programming Language :: Python :: 3.11
Classifier: Programming Language :: Python :: 3.12
Classifier: Programming Language :: Python
Classifier: Topic :: Games/Entertainment :: Role-Playing
Classifier: Topic :: Internet
Classifier: Topic :: Software Development :: Libraries :: Python Modules
Classifier: Topic :: Software Development :: Libraries
Classifier: Topic :: Software Development :: Libraries
Classifier: Topic :: Software Development
Classifier: Topic :: Text Processing :: Markup :: HTML
Classifier: Topic :: Utilities
Classifier: Typing :: Typed
Requires-Python: >=3.8
License-File: LICENSE
Requires-Dist: aiohttp-socks
Requires-Dist: aiohttp >=3.8
Requires-Dist: beautifulsoup4 >=4.0
Requires-Dist: html5lib >=1.1
Requires-Dist: lxml >=4.3.5
Requires-Dist: pydantic ~=2.0
Requires-Dist: typing-extensions
Provides-Extra: docs
Requires-Dist: sphinx ; extra == 'docs'
Requires-Dist: autodoc-pydantic >=2.0.0 ; extra == 'docs'
Requires-Dist: sphinx-autodoc-typehints ; extra == 'docs'
Provides-Extra: linting
Requires-Dist: ruff ; extra == 'linting'
Provides-Extra: server
Requires-Dist: fastapi >=0.109.1 ; extra == 'server'
Requires-Dist: uvicorn ; extra == 'server'
Provides-Extra: testing
Requires-Dist: aioresponses ; extra == 'testing'
Requires-Dist: asynctest ; extra == 'testing'
Requires-Dist: coverage[toml] ; extra == 'testing'
Requires-Dist: packaging ; extra == 'testing'
